pyqt_switch/__init__.py
pyqt_switch/pyqtSwitch.py
pyqt_switch-0.0.16.dist-info/LICENSE
pyqt_switch-0.0.16.dist-info/METADATA
pyqt_switch-0.0.16.dist-info/WHEEL
pyqt_switch-0.0.16.dist-info/top_level.txt
pyqt_switch-0.0.16.dist-info/RECORD
