Metadata-Version: 2.1
Name: pyqt-switch
Version: 0.0.16
Summary: PyQt Switch (O ) -> ( O)
Home-page: https://github.com/yjg30737/pyqt-switch.git
Author: Jung Gyu Yoon
Author-email: yjg30737@gmail.com
License: MIT
Platform: UNKNOWN
License-File: LICENSE
Requires-Dist: PyQt5 (>=5.8)
